cogclassifier/__init__.py
cogclassifier/__main__.py
cogclassifier/blast.py
cogclassifier/cog.py
cogclassifier/const.py
cogclassifier/logger.py
cogclassifier/main.py
cogclassifier/plot.py
cogclassifier/utils.py
cogclassifier/resources/cog_definition.tsv
cogclassifier/resources/cog_func_category.tsv
cogclassifier/scripts/__init__.py
cogclassifier/scripts/cogclassifier.py
cogclassifier/scripts/plot_cog_count_barchart.py
cogclassifier/scripts/plot_cog_count_piechart.py
cogclassifier-2.0.0.dist-info/METADATA
cogclassifier-2.0.0.dist-info/WHEEL
cogclassifier-2.0.0.dist-info/entry_points.txt
cogclassifier-2.0.0.dist-info/licenses/LICENSE
cogclassifier-2.0.0.dist-info/RECORD
