Metadata-Version: 2.3
Name: cogclassifier
Version: 2.0.0
Summary: A tool for classifying prokaryote protein sequences into COG functional category
Project-URL: repository, https://github.com/moshi4/COGclassifier/
Author: moshi4
License: MIT
Keywords: COG,bioinformatics,functional-analysis,functional-annotation,genomics
Classifier: Intended Audience :: Science/Research
Classifier: Topic :: Scientific/Engineering :: Bio-Informatics
Requires-Python: >=3.9
Requires-Dist: altair>=5.0.0
Requires-Dist: pandas>=2.0.0
Requires-Dist: pydantic>=2.11.3
Requires-Dist: requests>=2.27.1
Requires-Dist: typer>=0.15.2
Requires-Dist: vl-convert-python>=1.7.0
